pysoap/__init__.py
pysoap/envelope.py
py_soap-2026.1.4.dist-info/METADATA
py_soap-2026.1.4.dist-info/WHEEL
py_soap-2026.1.4.dist-info/top_level.txt
py_soap-2026.1.4.dist-info/RECORD
