Metadata-Version: 2.4
Name: py-soap
Version: 2026.1.4
Summary: SOAP client library
License-Expression: LGPL-3.0
Requires-Python: >=3.11
Requires-Dist: six
Requires-Dist: lxml
